jean_claude/__init__.py
jean_claude/cli/__init__.py
jean_claude/cli/main.py
jean_claude/cli/streaming.py
jean_claude/cli/commands/__init__.py
jean_claude/cli/commands/cleanup.py
jean_claude/cli/commands/dashboard.py
jean_claude/cli/commands/implement.py
jean_claude/cli/commands/init.py
jean_claude/cli/commands/initialize.py
jean_claude/cli/commands/logs.py
jean_claude/cli/commands/migrate.py
jean_claude/cli/commands/onboard.py
jean_claude/cli/commands/prime.py
jean_claude/cli/commands/prompt.py
jean_claude/cli/commands/run.py
jean_claude/cli/commands/status.py
jean_claude/cli/commands/upgrade.py
jean_claude/cli/commands/work.py
jean_claude/cli/commands/workflow.py
jean_claude/config/__init__.py
jean_claude/config/loader.py
jean_claude/config/models.py
jean_claude/coordination/__init__.py
jean_claude/core/__init__.py
jean_claude/core/agent.py
jean_claude/core/ambiguity_detector.py
jean_claude/core/beads.py
jean_claude/core/beads_trailer_formatter.py
jean_claude/core/blocker_detector.py
jean_claude/core/blocker_message_builder.py
jean_claude/core/commit_body_generator.py
jean_claude/core/commit_error_handler.py
jean_claude/core/commit_message_formatter.py
jean_claude/core/conventional_commit_parser.py
jean_claude/core/edit_and_revalidate.py
jean_claude/core/edit_task_handler.py
jean_claude/core/error_detector.py
jean_claude/core/event_store.py
jean_claude/core/events.py
jean_claude/core/feature_commit_orchestrator.py
jean_claude/core/file_utils.py
jean_claude/core/git_file_stager.py
jean_claude/core/inbox_count.py
jean_claude/core/inbox_count_persistence.py
jean_claude/core/inbox_writer.py
jean_claude/core/interactive_prompt_handler.py
jean_claude/core/mailbox_api.py
jean_claude/core/mailbox_directory_manager.py
jean_claude/core/mailbox_paths.py
jean_claude/core/mailbox_storage.py
jean_claude/core/message.py
jean_claude/core/message_reader.py
jean_claude/core/message_writer.py
jean_claude/core/outbox_monitor.py
jean_claude/core/response_parser.py
jean_claude-0.7.1.dist-info/METADATA
jean_claude-0.7.1.dist-info/WHEEL
jean_claude-0.7.1.dist-info/entry_points.txt
jean_claude-0.7.1.dist-info/RECORD
