Metadata-Version: 2.4
Name: jean-claude
Version: 0.7.1
Summary: Jean Claude CLI - AI-powered development workflows for any codebase
Project-URL: Homepage, https://github.com/joshuaoliphant/jean-claude
Project-URL: Documentation, https://github.com/joshuaoliphant/jean-claude#readme
Project-URL: Repository, https://github.com/joshuaoliphant/jean-claude
Project-URL: Issues, https://github.com/joshuaoliphant/jean-claude/issues
Author: Joshua Oliphant
License: MIT
Keywords: ai,automation,claude,cli,developer-tools,workflows
Classifier: Development Status :: 3 - Alpha
Classifier: Environment :: Console
Classifier: Intended Audience :: Developers
Classifier: License :: OSI Approved :: MIT License
Classifier: Programming Language :: Python :: 3
Classifier: Programming Language :: Python :: 3.10
Classifier: Programming Language :: Python :: 3.11
Classifier: Programming Language :: Python :: 3.12
Classifier: Topic :: Software Development :: Build Tools
Classifier: Topic :: Software Development :: Code Generators
Requires-Python: >=3.10
Requires-Dist: anyio>=4.0.0
Requires-Dist: claude-agent-sdk>=0.1.18
Requires-Dist: click>=8.0.0
Requires-Dist: fastapi>=0.127.0
Requires-Dist: jinja2>=3.0.0
Requires-Dist: pydantic>=2.0.0
Requires-Dist: python-dotenv>=1.0.0
Requires-Dist: pyyaml>=6.0.0
Requires-Dist: rich>=13.0.0
Requires-Dist: sse-starlette>=3.0.4
Requires-Dist: uvicorn>=0.40.0
Provides-Extra: dev
Requires-Dist: mypy>=1.0.0; extra == 'dev'
Requires-Dist: pytest-asyncio>=0.21.0; extra == 'dev'
Requires-Dist: pytest-cov>=4.0.0; extra == 'dev'
Requires-Dist: pytest>=7.0.0; extra == 'dev'
Requires-Dist: ruff>=0.1.0; extra == 'dev'
